matlab_simulink_mcp/__init__.py
matlab_simulink_mcp/__main__.py
matlab_simulink_mcp/functions.py
matlab_simulink_mcp/log_utils.py
matlab_simulink_mcp/security.py
matlab_simulink_mcp/server.py
matlab_simulink_mcp/state.py
matlab_simulink_mcp/data/__init__.py
matlab_simulink_mcp/data/blacklist.txt
matlab_simulink_mcp/data/simlib_db.json
matlab_simulink_mcp/data/helpers/describe_system.m
matlab_simulink_mcp/data/helpers/format_system.m
matlab_simulink_mcp/data/helpers/get_images.m
matlab_simulink_mcp/data/helpers/get_ports_connections.m
matlab_simulink_mcp/data/helpers/snapshot_system.m
matlab_simulink_mcp/data/helpers/validate_code.m
matlab_simulink_mcp/installer/__init__.py
matlab_simulink_mcp/installer/installer.py
matlab_simulink_mcp/installer/launcher.py
matlab_simulink_mcp/installer/win_elevate.py
matlab_simulink_mcp-0.1.5.dist-info/licenses/LICENSE
matlab_simulink_mcp-0.1.5.dist-info/METADATA
matlab_simulink_mcp-0.1.5.dist-info/WHEEL
matlab_simulink_mcp-0.1.5.dist-info/entry_points.txt
matlab_simulink_mcp-0.1.5.dist-info/top_level.txt
matlab_simulink_mcp-0.1.5.dist-info/RECORD
