Metadata-Version: 2.4
Name: matlab-simulink-mcp
Version: 0.1.5
Summary: An MCP server for allowing LLMs to interact with MATLAB and Simulink
Author: Rohail
License: MIT
Classifier: Development Status :: 3 - Alpha
Classifier: Intended Audience :: Developers
Classifier: License :: OSI Approved :: MIT License
Classifier: Programming Language :: Python :: 3
Classifier: Programming Language :: Python :: 3.10
Classifier: Programming Language :: Python :: 3.11
Classifier: Programming Language :: Python :: 3.12
Classifier: Topic :: Scientific/Engineering
Classifier: Topic :: Software Development :: Libraries :: Python Modules
Requires-Python: <3.13,>=3.10
License-File: LICENSE
Requires-Dist: fastmcp>=2.12.2
Requires-Dist: platformdirs>=4.4.0
Requires-Dist: setuptools>=80.9.0
Dynamic: license-file
